MANIFEST.in
README.md
pyproject.toml
setup.cfg
setup.py
baseapp_message_templates/__init__.py
baseapp_message_templates/admin.py
baseapp_message_templates/custom_templates.py
baseapp_message_templates/email_utils.py
baseapp_message_templates/filters.py
baseapp_message_templates/models.py
baseapp_message_templates/sendgrid.py
baseapp_message_templates/sms_utils.py
baseapp_message_templates/utils.py
baseapp_message_templates.egg-info/PKG-INFO
baseapp_message_templates.egg-info/SOURCES.txt
baseapp_message_templates.egg-info/dependency_links.txt
baseapp_message_templates.egg-info/requires.txt
baseapp_message_templates.egg-info/top_level.txt
baseapp_message_templates/migrations/0001_initial.py
baseapp_message_templates/migrations/0002_auto_20240108_1503.py
baseapp_message_templates/migrations/0003_alter_emailtemplate_name_alter_smstemplate_name.py
baseapp_message_templates/migrations/__init__.py
baseapp_message_templates/tests/__init__.py
baseapp_message_templates/tests/conftest.py
baseapp_message_templates/tests/factories.py
baseapp_message_templates/tests/test_migration_health_check.py
baseapp_message_templates/tests/unit/__init__.py
baseapp_message_templates/tests/unit/test_templates.py
testproject/__init__.py
testproject/settings.py